Metadata-Version: 2.1
Name: pytest-it
Version: 0.1.5
Summary: Pytest plugin to display test reports as a plaintext spec, inspired by Rspec: https://github.com/mattduck/pytest-it.
Home-page: https://github.com/mattduck/pytest-it
Author: Matt Duck
Author-email: matt@mattduck.com
Maintainer: Matt Duck
Maintainer-email: matt@mattduck.com
License: MIT
Keywords: pytest,pytest-it,test,bdd,rspec,org-mode,markdown
Classifier: Development Status :: 4 - Beta
Classifier: Framework :: Pytest
Classifier: Intended Audience :: Developers
Classifier: Topic :: Software Development :: Testing
Classifier: Natural Language :: English
Classifier: Programming Language :: Python
Classifier: Programming Language :: Python :: 2.7
Classifier: Programming Language :: Python :: 3.6
Classifier: Programming Language :: Python :: 3.7
Classifier: License :: OSI Approved :: MIT License
License-File: LICENSE
